email_client/__init__.py
email_client/server.py
mseep_email_client-0.1.1.dist-info/licenses/LICENSE
mseep_email_client-0.1.1.dist-info/METADATA
mseep_email_client-0.1.1.dist-info/WHEEL
mseep_email_client-0.1.1.dist-info/entry_points.txt
mseep_email_client-0.1.1.dist-info/top_level.txt
mseep_email_client-0.1.1.dist-info/RECORD
